slurm_tools/__init__.py
slurm_tools/slurm_logs.py
slurm_tools/slurm_tui.py
slurm_tools/snapshot.py
slurm_tools-0.1.0.dist-info/LICENSE
slurm_tools-0.1.0.dist-info/METADATA
slurm_tools-0.1.0.dist-info/WHEEL
slurm_tools-0.1.0.dist-info/entry_points.txt
slurm_tools-0.1.0.dist-info/RECORD
